requests_doh/__init__.py
requests_doh/adapter.py
requests_doh/cachemanager.py
requests_doh/exceptions.py
requests_doh/resolver.py
requests_doh/session.py
requests_doh/connector/__init__.py
requests_doh/connector/default.py
requests_doh/connector/proxies.py
requests_doh-1.0.0.dist-info/LICENSE
requests_doh-1.0.0.dist-info/METADATA
requests_doh-1.0.0.dist-info/WHEEL
requests_doh-1.0.0.dist-info/top_level.txt
requests_doh-1.0.0.dist-info/RECORD
