Metadata-Version: 2.1
Name: requests-doh
Version: 1.0.0
Summary: DNS over HTTPS resolver for python requests
Home-page: https://github.com/mansuf/requests-doh
Author: Rahman Yusuf
Author-email: danipart4@gmail.com
License: MIT
Keywords: requests,doh,dns,https,dns-over-https
Classifier: Development Status :: 5 - Production/Stable
Classifier: Intended Audience :: Developers
Classifier: Topic :: Internet :: Name Service (DNS)
Classifier: Topic :: Internet :: WWW/HTTP
Classifier: License :: OSI Approved :: MIT License
Classifier: Programming Language :: Python :: 3 :: Only
Classifier: Programming Language :: Python :: 3
Classifier: Programming Language :: Python :: 3.8
Classifier: Programming Language :: Python :: 3.9
Classifier: Programming Language :: Python :: 3.10
Requires-Python: >=3.8
License-File: LICENSE
Requires-Dist: requests[socks]==2.32.3
Requires-Dist: dnspython[doh]==2.6.1
Provides-Extra: docs
Requires-Dist: furo; extra == "docs"
Requires-Dist: myst-parser[linkify]; extra == "docs"
